LICENSE
MANIFEST.in
README.md
requirements.txt
setup.py
ocmd/__init__.py
ocmd/connection.py
ocmd/decorators.py
ocmd/ocp.py
ocmd/param.py
ocmd.egg-info/PKG-INFO
ocmd.egg-info/SOURCES.txt
ocmd.egg-info/dependency_links.txt
ocmd.egg-info/entry_points.txt
ocmd.egg-info/not-zip-safe
ocmd.egg-info/requires.txt
ocmd.egg-info/top_level.txt