Metadata-Version: 1.1
Name: ocmd
Version: 0.2.2
Summary: command-line tools for aliyun-oss
Home-page: http://github.com/skylothar/ocmd
Author: SkyLothar
Author-email: allothar@gmail.com
License: MIT
Platform: UNKNOWN
Classifier: Development Status :: 4 - Beta
Classifier: Intended Audience :: Developers
Classifier: Natural Language :: English
Classifier: License :: OSI Approved :: Apache Software License
Classifier: Programming Language :: Python
Classifier: Programming Language :: Python :: 2.7
Classifier: Programming Language :: Python :: 3
Classifier: Programming Language :: Python :: 3.3
Classifier: Programming Language :: Python :: 3.4
